{
  "version": 1,
  "author": "Shravani Sahare",
  "editor": "wokwi",
  "parts": [
    { "type": "board-esp32-devkit-c-v4", "id": "esp", "top": 0, "left": 43.24, "attrs": {} },
    { "type": "wokwi-dht22", "id": "dht1", "top": -28.5, "left": 215.4, "attrs": {} },
    { "type": "wokwi-potentiometer", "id": "pot1", "top": 56.3, "left": -192.2, "attrs": {} },
    {
      "type": "wokwi-photoresistor-sensor",
      "id": "ldr1",
      "top": 233.6,
      "left": -18.4,
      "attrs": {}
    },
    { "type": "wokwi-potentiometer", "id": "pot2", "top": -68.5, "left": -192.2, "attrs": {} },
    { "type": "wokwi-led", "id": "led1", "top": -90, "left": -44.2, "attrs": { "color": "red" } }
  ],
  "connections": [
    [ "esp:TX", "$serialMonitor:RX", "", [] ],
    [ "esp:RX", "$serialMonitor:TX", "", [] ],
    [ "dht1:VCC", "esp:3V3", "red", [ "v0", "h-38.4", "v-115.2", "h-144" ] ],
    [ "dht1:SDA", "esp:4", "green", [ "v0" ] ],
    [ "esp:GND.3", "dht1:GND", "black", [ "h14.44", "v38.4", "h9.6" ] ],
    [ "esp:GND.1", "pot2:GND", "black", [ "h-23.81", "v-115.2", "h-144" ] ],
    [ "esp:34", "pot2:SIG", "green", [ "h-14.21", "v-38.4", "h-144" ] ],
    [ "pot2:VCC", "esp:3V3", "red", [ "v19.2", "h8.8" ] ],
    [ "pot1:VCC", "esp:3V3", "red", [ "v19.2", "h152.8", "v-134.4" ] ],
    [ "pot1:GND", "esp:GND.1", "black", [ "v38.4", "h201.6", "v-9.6" ] ],
    [ "esp:35", "pot1:SIG", "green", [ "h-143.85", "v76.8", "h-57.6" ] ],
    [ "esp:GND.2", "ldr1:GND", "black", [ "v0", "h28.8", "v230.4" ] ],
    [ "ldr1:VCC", "esp:3V3", "red", [ "h38.4", "v-259.2", "h-153.6", "v9.6" ] ],
    [ "esp:15", "ldr1:AO", "green", [ "v0", "h76.8", "v105.6" ] ],
    [ "led1:A", "esp:25", "green", [ "v0" ] ],
    [ "led1:C", "esp:GND.2", "black", [ "v28.8", "h202", "v38.4" ] ]
  ],
  "dependencies": {}
}